[
    {
        "纳税人识别号": "132201199712115367",
        "纳税人名称": "张盼张冠涛",
        "金额合计（大写）": "伍仟贰佰叁拾捌元壹角",
        "房屋坐落": "丛台区城东街25号朝阳院1号楼4单元8号"
    },
    {
        "text": "中华人民共和国税收完税证明No.313045250300019073年3月5税务机关：分局国家税务总局邯郸市复兴区税务局第一税务填发日期：2025日纳税人识别号132201199712115367130429199711097334纳税人名称张盼张冠涛原凭证号税种品目名称税款所属时期入（退）库日期实缴（退）金额313046250300017306契税房屋买卖2025-03-05至2025-03-052025-03-055,238.10收据联交纳税人作完税证明金额合计伍仟贰佰叁拾捌元壹角5,238.10一般申报正税，税款所属机关：国家税务总局邯郸市复兴区税务局税务机关填票人11304040000，共有人：张盼，张冠涛房源编号：F13040420250004830房屋坐落地址：丛台区城东街25号朝阳院1号楼4单元8号建筑面积家1号：94.64平米交易面积：94.64平米合同日期：2025-03-05国复兴房产终端4首次打印妥善保管"
    }
]