[
    {
        "姓名": "物秀宋",
        "出生地": "河北省邯郸市复兴区",
        "籍贯": "河北省邯郸市复兴区",
        "出生日期": "1950年07月25日",
        "公民身份证件编号": "130402195007252427"
    },
    {
        "姓名": "李寅时",
        "出生地": "河北省邯郸市丛台区",
        "籍贯": "河北省郸市丛台区",
        "出生日期": "1948年09月20日",
        "公民身份证件编号": "1304021948809202435"
    },
    {
        "text": "常住人口登记1304033206786李定时姓名物秀宋要营用名性别女出生地河北省邯郸市复兴区民族汉箱贸河北省邯郸市复兴区出生日期1950年07月25日本市（县）其他住址宗教信仰公民身份130402195007252427身高167cn证件编号血型不明文化程度小学毕业婚姻状况已婚兵役状况未服兵投市肉食联合加工服务处所职何时由何地迁来本市（）专何时由何地迁来些所市华返出所房艳芳登记日2华旅承办人签章：日常住人口登记3040322005786李宝时姓名李寅时户户主曾名性别男出生地河北省邯郸市丛台区民族汉籍贯河北省郸市丛台区出生日期1948年09月20日本市（县）其他住址宗教信仰公民身份1304021948809202435证件编号身高72cm血型不明文化程度小学单业婚姻状况已婚兵役状况未服兵役服务处所邯郸铁路机务段职何时山何地迁来本市（县）户日丰川何时由何地迁来本址承办人签章：房艳芳登记华派日"
    }
]