[
    {
        "持证人": "张子明",
        "登记日期": "2008年09月01日",
        "结婚证字号": "语嘉字15085250",
        "男方姓名": "张子明",
        "男方国籍": "中国",
        "男方出生日期": "1985年02月09日",
        "男方身份证号": "130425198502090056",
        "女方姓名": "杨青",
        "女方国籍": "中国",
        "女方出生日期": "1985年11月10日",
        "女方身份证号": "130425198511100025"
    },
    {
        "text": "持证人张子明登记日期2008年09月01日结婚语嘉字15085250备注张子明姓名性别男中国国籍出生日期1985年02月09日130425198502090056身份证件号姓名杨青性别女国籍中国出生日期1985年11月10日身份证件号130425198511100025"
    }
]