[
    {
        "持证人": "樊品品",
        "登记日期": "2022年08月06日",
        "结婚证字号": "J130403-2022-001470",
        "男方姓名": "王程远",
        "男方国籍": "中国",
        "男方出生日期": "1995年01月20日",
        "男方身份证号": "130402199501200911",
        "女方姓名": "樊晶品",
        "女方国籍": "中国",
        "女方出生日期": "1993年08月07日",
        "女方身份证号": "13042819930807294X"
    },
    {
        "text": "e持证人樊品品登记日期2022年08月06日结婚证字号J130403-2022-001470备注姓名樊晶品性别女国籍中国出生日期1993年08月07日身份证件号13042819930807294X姓名王程远性别男国籍中国出生日期1995年01月20日身份证件号130402199501200911W"
    }
]